[
    {
        "db_id": "college_2",
        "complexity": "Simple",
        "sql": "SELECT name, tot_cred FROM student WHERE dept_name = 'History';",
        "result_summary": "Returns 117 rows listing the name and total credits for every student in the 'History' department.",
        "schema": "Database: college_2\n\nTable: classroom\nColumns: building, room_number, capacity\nSample Rows (Limit 3):\n- ('Lamberton', '134', 10)\n- ('Chandler', '375', 10)\n- ('Fairchild', '145', 27)\n\nTable: department\nColumns: dept_name, building, budget\nSample Rows (Limit 3):\n- ('Civil Eng.', 'Chandler', 255041.46)\n- ('Biology', 'Candlestick', 647610.55)\n- ('History', 'Taylor', 699140.86)\n\nTable: course\nColumns: course_id, title, dept_name, credits\nSample Rows (Limit 3):\n- ('787', 'C  Programming', 'Mech. Eng.', 4)\n- ('238', 'The Music of Donovan', 'Mech. Eng.', 3)\n- ('608', 'Electron Microscopy', 'Mech. Eng.', 3)\n\nTable: instructor\nColumns: ID, name, dept_name, salary\nSample Rows (Limit 3):\n- ('63395', 'McKinnon', 'Cybernetics', 94333.99)\n- ('78699', 'Pingr', 'Statistics', 59303.62)\n- ('96895', 'Mird', 'Marketing', 119921.41)\n\nTable: section\nColumns: course_id, sec_id, semester, year, building, room_number, time_slot_id\nSample Rows (Limit 3):\n- ('313', '1', 'Fall', 2010, 'Chandler', '804', 'N')\n- ('747', '1', 'Spring', 2004, 'Gates', '314', 'K')\n- ('443', '1', 'Spring', 2010, 'Whitman', '434', 'O')\n\nTable: teaches\nColumns: ID, course_id, sec_id, semester, year\nSample Rows (Limit 3):\n- ('34175', '747', '1', 'Spring', 2004)\n- ('3199', '169', '1', 'Spring', 2007)\n- ('6569', '445', '1', 'Spring', 2001)\n\nTable: student\nColumns: ID, name, dept_name, tot_cred\nSample Rows (Limit 3):\n- ('24746', 'Schrefl', 'History', 4)\n- ('79352', 'Rumat', 'Finance', 100)\n- ('76672', 'Miliko', 'Statistics', 116)\n\nTable: takes\nColumns: ID, course_id, sec_id, semester, year, grade\nSample Rows (Limit 3):\n- ('65901', '401', '1', 'Fall', 2003, 'C-')\n- ('24932', '802', '1', 'Spring', 2003, 'B-')\n- ('61332', '200', '1', 'Spring', 2007, 'A-')\n\nTable: advisor\nColumns: s_ID, i_ID\nSample Rows (Limit 3):\n- ('24746', '19368')\n- ('79352', '95030')\n- ('76672', '22591')\n\nTable: time_slot\nColumns: time_slot_id, day, start_hr, start_min, end_hr, end_min\nSample Rows (Limit 3):\n- ('A', 'M', 8, 0, 8, 50)\n- ('A', 'W', 8, 0, 8, 50)\n- ('A', 'F', 8, 0, 8, 50)\n\nTable: prereq\nColumns: course_id, prereq_id\nSample Rows (Limit 3):\n- ('376', '130')\n- ('760', '169')\n- ('403', '345')",
        "persona": "The Executive",
        "nl_question": "What are the names and total credits for all students in the History department?"
    },
    {
        "db_id": "college_2",
        "complexity": "Simple",
        "sql": "SELECT ID, name, salary FROM instructor WHERE dept_name = 'Cybernetics';",
        "result_summary": "Returns 4 rows listing the ID, name, and salary for each instructor belonging to the 'Cybernetics' department.",
        "schema": "Database: college_2\n\nTable: classroom\nColumns: building, room_number, capacity\nSample Rows (Limit 3):\n- ('Lamberton', '134', 10)\n- ('Chandler', '375', 10)\n- ('Fairchild', '145', 27)\n\nTable: department\nColumns: dept_name, building, budget\nSample Rows (Limit 3):\n- ('Civil Eng.', 'Chandler', 255041.46)\n- ('Biology', 'Candlestick', 647610.55)\n- ('History', 'Taylor', 699140.86)\n\nTable: course\nColumns: course_id, title, dept_name, credits\nSample Rows (Limit 3):\n- ('787', 'C  Programming', 'Mech. Eng.', 4)\n- ('238', 'The Music of Donovan', 'Mech. Eng.', 3)\n- ('608', 'Electron Microscopy', 'Mech. Eng.', 3)\n\nTable: instructor\nColumns: ID, name, dept_name, salary\nSample Rows (Limit 3):\n- ('63395', 'McKinnon', 'Cybernetics', 94333.99)\n- ('78699', 'Pingr', 'Statistics', 59303.62)\n- ('96895', 'Mird', 'Marketing', 119921.41)\n\nTable: section\nColumns: course_id, sec_id, semester, year, building, room_number, time_slot_id\nSample Rows (Limit 3):\n- ('313', '1', 'Fall', 2010, 'Chandler', '804', 'N')\n- ('747', '1', 'Spring', 2004, 'Gates', '314', 'K')\n- ('443', '1', 'Spring', 2010, 'Whitman', '434', 'O')\n\nTable: teaches\nColumns: ID, course_id, sec_id, semester, year\nSample Rows (Limit 3):\n- ('34175', '747', '1', 'Spring', 2004)\n- ('3199', '169', '1', 'Spring', 2007)\n- ('6569', '445', '1', 'Spring', 2001)\n\nTable: student\nColumns: ID, name, dept_name, tot_cred\nSample Rows (Limit 3):\n- ('24746', 'Schrefl', 'History', 4)\n- ('79352', 'Rumat', 'Finance', 100)\n- ('76672', 'Miliko', 'Statistics', 116)\n\nTable: takes\nColumns: ID, course_id, sec_id, semester, year, grade\nSample Rows (Limit 3):\n- ('65901', '401', '1', 'Fall', 2003, 'C-')\n- ('24932', '802', '1', 'Spring', 2003, 'B-')\n- ('61332', '200', '1', 'Spring', 2007, 'A-')\n\nTable: advisor\nColumns: s_ID, i_ID\nSample Rows (Limit 3):\n- ('24746', '19368')\n- ('79352', '95030')\n- ('76672', '22591')\n\nTable: time_slot\nColumns: time_slot_id, day, start_hr, start_min, end_hr, end_min\nSample Rows (Limit 3):\n- ('A', 'M', 8, 0, 8, 50)\n- ('A', 'W', 8, 0, 8, 50)\n- ('A', 'F', 8, 0, 8, 50)\n\nTable: prereq\nColumns: course_id, prereq_id\nSample Rows (Limit 3):\n- ('376', '130')\n- ('760', '169')\n- ('403', '345')",
        "persona": "The Data Analyst",
        "nl_question": "What are the ID, name, and salary details for instructors in the 'Cybernetics' department?"
    },
    {
        "db_id": "college_2",
        "complexity": "Simple",
        "sql": "SELECT course_id, title, dept_name FROM course WHERE credits = 4;",
        "result_summary": "Returns 92 rows listing the course ID, title, and department name for all courses that are worth exactly 4 credits.",
        "schema": "Database: college_2\n\nTable: classroom\nColumns: building, room_number, capacity\nSample Rows (Limit 3):\n- ('Lamberton', '134', 10)\n- ('Chandler', '375', 10)\n- ('Fairchild', '145', 27)\n\nTable: department\nColumns: dept_name, building, budget\nSample Rows (Limit 3):\n- ('Civil Eng.', 'Chandler', 255041.46)\n- ('Biology', 'Candlestick', 647610.55)\n- ('History', 'Taylor', 699140.86)\n\nTable: course\nColumns: course_id, title, dept_name, credits\nSample Rows (Limit 3):\n- ('787', 'C  Programming', 'Mech. Eng.', 4)\n- ('238', 'The Music of Donovan', 'Mech. Eng.', 3)\n- ('608', 'Electron Microscopy', 'Mech. Eng.', 3)\n\nTable: instructor\nColumns: ID, name, dept_name, salary\nSample Rows (Limit 3):\n- ('63395', 'McKinnon', 'Cybernetics', 94333.99)\n- ('78699', 'Pingr', 'Statistics', 59303.62)\n- ('96895', 'Mird', 'Marketing', 119921.41)\n\nTable: section\nColumns: course_id, sec_id, semester, year, building, room_number, time_slot_id\nSample Rows (Limit 3):\n- ('313', '1', 'Fall', 2010, 'Chandler', '804', 'N')\n- ('747', '1', 'Spring', 2004, 'Gates', '314', 'K')\n- ('443', '1', 'Spring', 2010, 'Whitman', '434', 'O')\n\nTable: teaches\nColumns: ID, course_id, sec_id, semester, year\nSample Rows (Limit 3):\n- ('34175', '747', '1', 'Spring', 2004)\n- ('3199', '169', '1', 'Spring', 2007)\n- ('6569', '445', '1', 'Spring', 2001)\n\nTable: student\nColumns: ID, name, dept_name, tot_cred\nSample Rows (Limit 3):\n- ('24746', 'Schrefl', 'History', 4)\n- ('79352', 'Rumat', 'Finance', 100)\n- ('76672', 'Miliko', 'Statistics', 116)\n\nTable: takes\nColumns: ID, course_id, sec_id, semester, year, grade\nSample Rows (Limit 3):\n- ('65901', '401', '1', 'Fall', 2003, 'C-')\n- ('24932', '802', '1', 'Spring', 2003, 'B-')\n- ('61332', '200', '1', 'Spring', 2007, 'A-')\n\nTable: advisor\nColumns: s_ID, i_ID\nSample Rows (Limit 3):\n- ('24746', '19368')\n- ('79352', '95030')\n- ('76672', '22591')\n\nTable: time_slot\nColumns: time_slot_id, day, start_hr, start_min, end_hr, end_min\nSample Rows (Limit 3):\n- ('A', 'M', 8, 0, 8, 50)\n- ('A', 'W', 8, 0, 8, 50)\n- ('A', 'F', 8, 0, 8, 50)\n\nTable: prereq\nColumns: course_id, prereq_id\nSample Rows (Limit 3):\n- ('376', '130')\n- ('760', '169')\n- ('403', '345')",
        "persona": "The Product Manager",
        "nl_question": "To better understand our curriculum offerings, could you list the course ID, title, and department name for all courses that are worth exactly 4 credits?"
    },
    {
        "db_id": "college_2",
        "complexity": "Simple",
        "sql": "SELECT dept_name, budget FROM department ORDER BY budget DESC;",
        "result_summary": "Returns 20 rows listing each department's name and its corresponding budget, ordered from the highest budget to the lowest.",
        "schema": "Database: college_2\n\nTable: classroom\nColumns: building, room_number, capacity\nSample Rows (Limit 3):\n- ('Lamberton', '134', 10)\n- ('Chandler', '375', 10)\n- ('Fairchild', '145', 27)\n\nTable: department\nColumns: dept_name, building, budget\nSample Rows (Limit 3):\n- ('Civil Eng.', 'Chandler', 255041.46)\n- ('Biology', 'Candlestick', 647610.55)\n- ('History', 'Taylor', 699140.86)\n\nTable: course\nColumns: course_id, title, dept_name, credits\nSample Rows (Limit 3):\n- ('787', 'C  Programming', 'Mech. Eng.', 4)\n- ('238', 'The Music of Donovan', 'Mech. Eng.', 3)\n- ('608', 'Electron Microscopy', 'Mech. Eng.', 3)\n\nTable: instructor\nColumns: ID, name, dept_name, salary\nSample Rows (Limit 3):\n- ('63395', 'McKinnon', 'Cybernetics', 94333.99)\n- ('78699', 'Pingr', 'Statistics', 59303.62)\n- ('96895', 'Mird', 'Marketing', 119921.41)\n\nTable: section\nColumns: course_id, sec_id, semester, year, building, room_number, time_slot_id\nSample Rows (Limit 3):\n- ('313', '1', 'Fall', 2010, 'Chandler', '804', 'N')\n- ('747', '1', 'Spring', 2004, 'Gates', '314', 'K')\n- ('443', '1', 'Spring', 2010, 'Whitman', '434', 'O')\n\nTable: teaches\nColumns: ID, course_id, sec_id, semester, year\nSample Rows (Limit 3):\n- ('34175', '747', '1', 'Spring', 2004)\n- ('3199', '169', '1', 'Spring', 2007)\n- ('6569', '445', '1', 'Spring', 2001)\n\nTable: student\nColumns: ID, name, dept_name, tot_cred\nSample Rows (Limit 3):\n- ('24746', 'Schrefl', 'History', 4)\n- ('79352', 'Rumat', 'Finance', 100)\n- ('76672', 'Miliko', 'Statistics', 116)\n\nTable: takes\nColumns: ID, course_id, sec_id, semester, year, grade\nSample Rows (Limit 3):\n- ('65901', '401', '1', 'Fall', 2003, 'C-')\n- ('24932', '802', '1', 'Spring', 2003, 'B-')\n- ('61332', '200', '1', 'Spring', 2007, 'A-')\n\nTable: advisor\nColumns: s_ID, i_ID\nSample Rows (Limit 3):\n- ('24746', '19368')\n- ('79352', '95030')\n- ('76672', '22591')\n\nTable: time_slot\nColumns: time_slot_id, day, start_hr, start_min, end_hr, end_min\nSample Rows (Limit 3):\n- ('A', 'M', 8, 0, 8, 50)\n- ('A', 'W', 8, 0, 8, 50)\n- ('A', 'F', 8, 0, 8, 50)\n\nTable: prereq\nColumns: course_id, prereq_id\nSample Rows (Limit 3):\n- ('376', '130')\n- ('760', '169')\n- ('403', '345')",
        "persona": "The Product Manager",
        "nl_question": "For strategic resource planning, can we get a report showing each department's name and its budget, ordered from the highest budget to the lowest?"
    }
]